cobanov_v2/__init__.py
cobanov_v2/main.py
cobanov_v2-0.1.0.dist-info/LICENSE
cobanov_v2-0.1.0.dist-info/METADATA
cobanov_v2-0.1.0.dist-info/WHEEL
cobanov_v2-0.1.0.dist-info/entry_points.txt
cobanov_v2-0.1.0.dist-info/top_level.txt
cobanov_v2-0.1.0.dist-info/RECORD
