Metadata-Version: 2.1
Name: cobanov-v2
Version: 0.1.0
Summary: cobanov command line tool
Home-page: https://github.com/cobanov/cobanov
Author: Your Name
Author-email: your.email@example.com
Classifier: Programming Language :: Python :: 3
Classifier: License :: OSI Approved :: MIT License
Classifier: Operating System :: OS Independent
Requires-Python: >=3.6
License-File: LICENSE
